pyetl/__init__.py
pyetl/connections.py
pyetl/dataset.py
pyetl/es.py
pyetl/mapping.py
pyetl/reader.py
pyetl/task.py
pyetl/utils.py
pyetl/writer.py
pyetl-2.2.2.dist-info/LICENSE
pyetl-2.2.2.dist-info/METADATA
pyetl-2.2.2.dist-info/WHEEL
pyetl-2.2.2.dist-info/top_level.txt
pyetl-2.2.2.dist-info/zip-safe
pyetl-2.2.2.dist-info/RECORD
