Metadata-Version: 2.1
Name: pyetl
Version: 2.2.2
Summary: Python ETL Frame
Home-page: https://github.com/taogeYT/pyetl
Author: liyatao
Author-email: li_yatao@outlook.com
License: Apache 2.0
Platform: UNKNOWN
Classifier: Development Status :: 5 - Production/Stable
Classifier: Intended Audience :: Developers
Classifier: License :: OSI Approved :: Apache Software License
Classifier: Programming Language :: Python
Classifier: Programming Language :: Python :: 3.6
Classifier: Programming Language :: Python :: 3.7
Classifier: Programming Language :: Python :: 3.8
Requires-Python: >=3.6
Requires-Dist: pydbclib (>=2.2.2)
Requires-Dist: pandas (>=0.22)
Requires-Dist: elasticsearch
Requires-Dist: sqlalchemy
